teds_core/__init__.py
teds_core/cache.py
teds_core/cli.py
teds_core/errors.py
teds_core/generate.py
teds_core/refs.py
teds_core/report.py
teds_core/resources.py
teds_core/utils.py
teds_core/validate.py
teds_core/version.py
teds_core/yamlio.py
teds_core/spec_schema.yaml
teds_core/teds_compat.yaml
teds_core/template_map.yaml
teds_core/templates/default.adoc.j2
teds_core/templates/default.html.j2
teds_core/templates/default.md.j2
teds_core/templates/summary.html.j2
teds_core/templates/summary.md.j2
teds-0.8.1.dist-info/METADATA
teds-0.8.1.dist-info/WHEEL
teds-0.8.1.dist-info/entry_points.txt
teds-0.8.1.dist-info/RECORD
