Metadata-Version: 2.4
Name: teds
Version: 0.8.1
Summary: TeDS (Test-Driven Schema Development Tool) - CLI for verifying JSON Schema contracts using YAML test specifications
Project-URL: Homepage, https://github.com/yaccob/teds
Project-URL: Repository, https://github.com/yaccob/teds.git
Project-URL: Issues, https://github.com/yaccob/teds/issues
Project-URL: Changelog, https://github.com/yaccob/teds/releases
Author: TeDS Authors
License: MIT
Keywords: cli,jsonschema,testing,yaml
Classifier: Environment :: Console
Classifier: License :: OSI Approved :: MIT License
Classifier: Programming Language :: Python :: 3
Classifier: Programming Language :: Python :: 3 :: Only
Classifier: Programming Language :: Python :: 3.10
Classifier: Programming Language :: Python :: 3.11
Classifier: Programming Language :: Python :: 3.12
Classifier: Topic :: Software Development :: Testing
Requires-Python: >=3.10
Requires-Dist: jinja2>=3.1
Requires-Dist: jsonpath-ng>=1.6.0
Requires-Dist: jsonschema[format-nongpl]>=4.22.0
Requires-Dist: referencing>=0.35.0
Requires-Dist: ruamel-yaml>=0.18.6
Requires-Dist: semver>=3.0.0
